colour_sort/__init__.py
colour_sort/all.npy
colour_sort/cli.py
colour_sort/image.py
colour_sort/sort.py
colour_sort/sort_type.py
colour_sort/verify.py
colour_sort-0.1.3.dist-info/entry_points.txt
colour_sort-0.1.3.dist-info/WHEEL
colour_sort-0.1.3.dist-info/METADATA
colour_sort-0.1.3.dist-info/RECORD
