Metadata-Version: 2.1
Name: colour-sort
Version: 0.1.3
Summary: A tool to generate images using all rgb colours with no duplicates.
Home-page: https://github.com/buckley-w-david/colour_sort
License: MIT
Author: David Buckley
Author-email: buckley.w.david@gmail.com
Requires-Python: >=3.6.7
Classifier: License :: OSI Approved :: MIT License
Classifier: Programming Language :: Python :: 3
Classifier: Programming Language :: Python :: 3.7
Classifier: Programming Language :: Python :: 3.8
Classifier: Topic :: Software Development :: Libraries :: Python Modules
Requires-Dist: importlib_resources (>=1.0,<2.0)
Requires-Dist: numpy (>=1.17,<2.0)
Requires-Dist: pillow (>=6.2,<7.0)
Project-URL: Repository, https://github.com/buckley-w-david/colour_sort
